{
    "data": [
        {
            "stop_id": "",
            "headsign": "Grillenweg",
            "platform": "",
            "patform_type": "",
            "time": 1736547180,
            "realtime": 1736547180,
            "line": {
                "name": "9",
                "type": "Bus",
                "bg_color": "#FF7800",
                "fg_color": "#FFFFFF",
                "product_icon": "/images/jpapi_hafas/bus.svg",
                "operator": "SVL"
            },
            "cancelled": false
        },
        {
            "stop_id": "",
            "headsign": "Bad Schwartau ZOB",
            "platform": "",
            "patform_type": "",
            "time": 1736547420,
            "realtime": 1736547420,
            "line": {
                "name": "7",
                "type": "Bus",
                "bg_color": "#FF7800",
                "fg_color": "#FFFFFF",
                "product_icon": "/images/jpapi_hafas/bus.svg",
                "operator": "SVL"
            },
            "cancelled": false
        },
        {
            "stop_id": "",
            "headsign": "Stephensonstra\u00dfe",
            "platform": "",
            "patform_type": "",
            "time": 1736548980,
            "realtime": 1736548980,
            "line": {
                "name": "7",
                "type": "Bus",
                "bg_color": "#FF7800",
                "fg_color": "#FFFFFF",
                "product_icon": "/images/jpapi_hafas/bus.svg",
                "operator": "SVL"
            },
            "cancelled": false
        },
        {
            "stop_id": "",
            "headsign": "Bad Schwartau ZOB",
            "platform": "",
            "patform_type": "",
            "time": 1736549400,
            "realtime": 1736549400,
            "line": {
                "name": "9",
                "type": "Bus",
                "bg_color": "#FF7800",
                "fg_color": "#FFFFFF",
                "product_icon": "/images/jpapi_hafas/bus.svg",
                "operator": "SVL"
            },
            "cancelled": false
        },
        {
            "stop_id": "",
            "headsign": "ZOB/Hauptbahnhof",
            "platform": "",
            "patform_type": "",
            "time": 1736550780,
            "realtime": 1736550780,
            "line": {
                "name": "7",
                "type": "Bus",
                "bg_color": "#FF7800",
                "fg_color": "#FFFFFF",
                "product_icon": "/images/jpapi_hafas/bus.svg",
                "operator": "SVL"
            },
            "cancelled": false
        },
        {
            "stop_id": "",
            "headsign": "Bad Schwartau ZOB",
            "platform": "",
            "patform_type": "",
            "time": 1736551020,
            "realtime": 1736551020,
            "line": {
                "name": "7",
                "type": "Bus",
                "bg_color": "#FF7800",
                "fg_color": "#FFFFFF",
                "product_icon": "/images/jpapi_hafas/bus.svg",
                "operator": "SVL"
            },
            "cancelled": false
        },
        {
            "stop_id": "",
            "headsign": "Bad Schwartau ZOB",
            "platform": "",
            "patform_type": "",
            "time": 1736553000,
            "realtime": 1736553000,
            "line": {
                "name": "7",
                "type": "Bus",
                "bg_color": "#FF7800",
                "fg_color": "#FFFFFF",
                "product_icon": "/images/jpapi_hafas/bus.svg",
                "operator": "SVL"
            },
            "cancelled": false
        },
        {
            "stop_id": "",
            "headsign": "Sereetzer Weg",
            "platform": "",
            "patform_type": "",
            "time": 1736553000,
            "realtime": 1736553000,
            "line": {
                "name": "9",
                "type": "Bus",
                "bg_color": "#FF7800",
                "fg_color": "#FFFFFF",
                "product_icon": "/images/jpapi_hafas/bus.svg",
                "operator": "SVL"
            },
            "cancelled": false
        },
        {
            "stop_id": "",
            "headsign": "Bahnhof Moisling",
            "platform": "",
            "patform_type": "",
            "time": 1736568420,
            "realtime": 1736568420,
            "line": {
                "name": "7",
                "type": "Bus",
                "bg_color": "#FF7800",
                "fg_color": "#FFFFFF",
                "product_icon": "/images/jpapi_hafas/bus.svg",
                "operator": "SVL"
            },
            "cancelled": false
        },
        {
            "stop_id": "",
            "headsign": "Grillenweg",
            "platform": "",
            "patform_type": "",
            "time": 1736569200,
            "realtime": 1736569200,
            "line": {
                "name": "9",
                "type": "Bus",
                "bg_color": "#FF7800",
                "fg_color": "#FFFFFF",
                "product_icon": "/images/jpapi_hafas/bus.svg",
                "operator": "SVL"
            },
            "cancelled": false
        },
        {
            "stop_id": "",
            "headsign": "Bahnhof Moisling",
            "platform": "",
            "patform_type": "",
            "time": 1736569920,
            "realtime": 1736569920,
            "line": {
                "name": "7",
                "type": "Bus",
                "bg_color": "#FF7800",
                "fg_color": "#FFFFFF",
                "product_icon": "/images/jpapi_hafas/bus.svg",
                "operator": "SVL"
            },
            "cancelled": false
        },
        {
            "stop_id": "",
            "headsign": "Bad Schwartau ZOB",
            "platform": "",
            "patform_type": "",
            "time": 1736570400,
            "realtime": 1736570400,
            "line": {
                "name": "7",
                "type": "Bus",
                "bg_color": "#FF7800",
                "fg_color": "#FFFFFF",
                "product_icon": "/images/jpapi_hafas/bus.svg",
                "operator": "SVL"
            },
            "cancelled": false
        },
        {
            "stop_id": "",
            "headsign": "Bad Schwartau ZOB",
            "platform": "",
            "patform_type": "",
            "time": 1736571420,
            "realtime": 1736571420,
            "line": {
                "name": "9",
                "type": "Bus",
                "bg_color": "#FF7800",
                "fg_color": "#FFFFFF",
                "product_icon": "/images/jpapi_hafas/bus.svg",
                "operator": "SVL"
            },
            "cancelled": false
        },
        {
            "stop_id": "",
            "headsign": "Bad Schwartau ZOB",
            "platform": "",
            "patform_type": "",
            "time": 1736571900,
            "realtime": 1736571900,
            "line": {
                "name": "7",
                "type": "Bus",
                "bg_color": "#FF7800",
                "fg_color": "#FFFFFF",
                "product_icon": "/images/jpapi_hafas/bus.svg",
                "operator": "SVL"
            },
            "cancelled": false
        },
        {
            "stop_id": "",
            "headsign": "Bahnhof Moisling",
            "platform": "",
            "patform_type": "",
            "time": 1736572020,
            "realtime": 1736572020,
            "line": {
                "name": "7",
                "type": "Bus",
                "bg_color": "#FF7800",
                "fg_color": "#FFFFFF",
                "product_icon": "/images/jpapi_hafas/bus.svg",
                "operator": "SVL"
            },
            "cancelled": false
        },
        {
            "stop_id": "",
            "headsign": "Grillenweg",
            "platform": "",
            "patform_type": "",
            "time": 1736572800,
            "realtime": 1736572800,
            "line": {
                "name": "9",
                "type": "Bus",
                "bg_color": "#FF7800",
                "fg_color": "#FFFFFF",
                "product_icon": "/images/jpapi_hafas/bus.svg",
                "operator": "SVL"
            },
            "cancelled": false
        },
        {
            "stop_id": "",
            "headsign": "Bahnhof Moisling",
            "platform": "",
            "patform_type": "",
            "time": 1736573520,
            "realtime": 1736573520,
            "line": {
                "name": "7",
                "type": "Bus",
                "bg_color": "#FF7800",
                "fg_color": "#FFFFFF",
                "product_icon": "/images/jpapi_hafas/bus.svg",
                "operator": "SVL"
            },
            "cancelled": false
        },
        {
            "stop_id": "",
            "headsign": "Bad Schwartau ZOB",
            "platform": "",
            "patform_type": "",
            "time": 1736574000,
            "realtime": 1736574000,
            "line": {
                "name": "7",
                "type": "Bus",
                "bg_color": "#FF7800",
                "fg_color": "#FFFFFF",
                "product_icon": "/images/jpapi_hafas/bus.svg",
                "operator": "SVL"
            },
            "cancelled": false
        },
        {
            "stop_id": "",
            "headsign": "Bad Schwartau ZOB",
            "platform": "",
            "patform_type": "",
            "time": 1736575020,
            "realtime": 1736575020,
            "line": {
                "name": "9",
                "type": "Bus",
                "bg_color": "#FF7800",
                "fg_color": "#FFFFFF",
                "product_icon": "/images/jpapi_hafas/bus.svg",
                "operator": "SVL"
            },
            "cancelled": false
        },
        {
            "stop_id": "",
            "headsign": "Bad Schwartau ZOB",
            "platform": "",
            "patform_type": "",
            "time": 1736575500,
            "realtime": 1736575500,
            "line": {
                "name": "7",
                "type": "Bus",
                "bg_color": "#FF7800",
                "fg_color": "#FFFFFF",
                "product_icon": "/images/jpapi_hafas/bus.svg",
                "operator": "SVL"
            },
            "cancelled": false
        },
        {
            "stop_id": "",
            "headsign": "Bahnhof Moisling",
            "platform": "",
            "patform_type": "",
            "time": 1736576160,
            "realtime": 1736576160,
            "line": {
                "name": "7",
                "type": "Bus",
                "bg_color": "#FF7800",
                "fg_color": "#FFFFFF",
                "product_icon": "/images/jpapi_hafas/bus.svg",
                "operator": "SVL"
            },
            "cancelled": false
        },
        {
            "stop_id": "",
            "headsign": "Grillenweg",
            "platform": "",
            "patform_type": "",
            "time": 1736576340,
            "realtime": 1736576340,
            "line": {
                "name": "9",
                "type": "Bus",
                "bg_color": "#FF7800",
                "fg_color": "#FFFFFF",
                "product_icon": "/images/jpapi_hafas/bus.svg",
                "operator": "SVL"
            },
            "cancelled": false
        },
        {
            "stop_id": "",
            "headsign": "Bad Schwartau ZOB",
            "platform": "",
            "patform_type": "",
            "time": 1736577900,
            "realtime": 1736577900,
            "line": {
                "name": "7",
                "type": "Bus",
                "bg_color": "#FF7800",
                "fg_color": "#FFFFFF",
                "product_icon": "/images/jpapi_hafas/bus.svg",
                "operator": "SVL"
            },
            "cancelled": false
        },
        {
            "stop_id": "",
            "headsign": "Bahnhof Moisling",
            "platform": "",
            "patform_type": "",
            "time": 1736577960,
            "realtime": 1736577960,
            "line": {
                "name": "7",
                "type": "Bus",
                "bg_color": "#FF7800",
                "fg_color": "#FFFFFF",
                "product_icon": "/images/jpapi_hafas/bus.svg",
                "operator": "SVL"
            },
            "cancelled": false
        },
        {
            "stop_id": "",
            "headsign": "Bad Schwartau ZOB",
            "platform": "",
            "patform_type": "",
            "time": 1736579580,
            "realtime": 1736579580,
            "line": {
                "name": "9",
                "type": "Bus",
                "bg_color": "#FF7800",
                "fg_color": "#FFFFFF",
                "product_icon": "/images/jpapi_hafas/bus.svg",
                "operator": "SVL"
            },
            "cancelled": false
        },
        {
            "stop_id": "",
            "headsign": "Bad Schwartau ZOB",
            "platform": "",
            "patform_type": "",
            "time": 1736579700,
            "realtime": 1736579700,
            "line": {
                "name": "7",
                "type": "Bus",
                "bg_color": "#FF7800",
                "fg_color": "#FFFFFF",
                "product_icon": "/images/jpapi_hafas/bus.svg",
                "operator": "SVL"
            },
            "cancelled": false
        },
        {
            "stop_id": "",
            "headsign": "Bahnhof Moisling",
            "platform": "",
            "patform_type": "",
            "time": 1736579760,
            "realtime": 1736579760,
            "line": {
                "name": "7",
                "type": "Bus",
                "bg_color": "#FF7800",
                "fg_color": "#FFFFFF",
                "product_icon": "/images/jpapi_hafas/bus.svg",
                "operator": "SVL"
            },
            "cancelled": false
        },
        {
            "stop_id": "",
            "headsign": "Grillenweg",
            "platform": "",
            "patform_type": "",
            "time": 1736579940,
            "realtime": 1736579940,
            "line": {
                "name": "9",
                "type": "Bus",
                "bg_color": "#FF7800",
                "fg_color": "#FFFFFF",
                "product_icon": "/images/jpapi_hafas/bus.svg",
                "operator": "SVL"
            },
            "cancelled": false
        },
        {
            "stop_id": "",
            "headsign": "Bad Schwartau ZOB",
            "platform": "",
            "patform_type": "",
            "time": 1736581500,
            "realtime": 1736581500,
            "line": {
                "name": "7",
                "type": "Bus",
                "bg_color": "#FF7800",
                "fg_color": "#FFFFFF",
                "product_icon": "/images/jpapi_hafas/bus.svg",
                "operator": "SVL"
            },
            "cancelled": false
        },
        {
            "stop_id": "",
            "headsign": "Bahnhof Moisling",
            "platform": "",
            "patform_type": "",
            "time": 1736581560,
            "realtime": 1736581560,
            "line": {
                "name": "7",
                "type": "Bus",
                "bg_color": "#FF7800",
                "fg_color": "#FFFFFF",
                "product_icon": "/images/jpapi_hafas/bus.svg",
                "operator": "SVL"
            },
            "cancelled": false
        },
        {
            "stop_id": "",
            "headsign": "Bornkamp",
            "platform": "",
            "patform_type": "",
            "time": 1736581740,
            "realtime": 1736581740,
            "line": {
                "name": "9",
                "type": "Bus",
                "bg_color": "#FF7800",
                "fg_color": "#FFFFFF",
                "product_icon": "/images/jpapi_hafas/bus.svg",
                "operator": "SVL"
            },
            "cancelled": false
        },
        {
            "stop_id": "",
            "headsign": "Bad Schwartau ZOB",
            "platform": "",
            "patform_type": "",
            "time": 1736583180,
            "realtime": 1736583180,
            "line": {
                "name": "9",
                "type": "Bus",
                "bg_color": "#FF7800",
                "fg_color": "#FFFFFF",
                "product_icon": "/images/jpapi_hafas/bus.svg",
                "operator": "SVL"
            },
            "cancelled": false
        },
        {
            "stop_id": "",
            "headsign": "Bad Schwartau ZOB",
            "platform": "",
            "patform_type": "",
            "time": 1736583300,
            "realtime": 1736583300,
            "line": {
                "name": "7",
                "type": "Bus",
                "bg_color": "#FF7800",
                "fg_color": "#FFFFFF",
                "product_icon": "/images/jpapi_hafas/bus.svg",
                "operator": "SVL"
            },
            "cancelled": false
        },
        {
            "stop_id": "",
            "headsign": "Bahnhof Moisling",
            "platform": "",
            "patform_type": "",
            "time": 1736583360,
            "realtime": 1736583360,
            "line": {
                "name": "7",
                "type": "Bus",
                "bg_color": "#FF7800",
                "fg_color": "#FFFFFF",
                "product_icon": "/images/jpapi_hafas/bus.svg",
                "operator": "SVL"
            },
            "cancelled": false
        },
        {
            "stop_id": "",
            "headsign": "Grillenweg",
            "platform": "",
            "patform_type": "",
            "time": 1736583540,
            "realtime": 1736583540,
            "line": {
                "name": "9",
                "type": "Bus",
                "bg_color": "#FF7800",
                "fg_color": "#FFFFFF",
                "product_icon": "/images/jpapi_hafas/bus.svg",
                "operator": "SVL"
            },
            "cancelled": false
        },
        {
            "stop_id": "",
            "headsign": "Bad Schwartau ZOB",
            "platform": "",
            "patform_type": "",
            "time": 1736584980,
            "realtime": 1736584980,
            "line": {
                "name": "9",
                "type": "Bus",
                "bg_color": "#FF7800",
                "fg_color": "#FFFFFF",
                "product_icon": "/images/jpapi_hafas/bus.svg",
                "operator": "SVL"
            },
            "cancelled": false
        },
        {
            "stop_id": "",
            "headsign": "Bad Schwartau ZOB",
            "platform": "",
            "patform_type": "",
            "time": 1736585100,
            "realtime": 1736585100,
            "line": {
                "name": "7",
                "type": "Bus",
                "bg_color": "#FF7800",
                "fg_color": "#FFFFFF",
                "product_icon": "/images/jpapi_hafas/bus.svg",
                "operator": "SVL"
            },
            "cancelled": false
        },
        {
            "stop_id": "",
            "headsign": "Bahnhof Moisling",
            "platform": "",
            "patform_type": "",
            "time": 1736585160,
            "realtime": 1736585160,
            "line": {
                "name": "7",
                "type": "Bus",
                "bg_color": "#FF7800",
                "fg_color": "#FFFFFF",
                "product_icon": "/images/jpapi_hafas/bus.svg",
                "operator": "SVL"
            },
            "cancelled": false
        },
        {
            "stop_id": "",
            "headsign": "Bornkamp",
            "platform": "",
            "patform_type": "",
            "time": 1736585340,
            "realtime": 1736585340,
            "line": {
                "name": "9",
                "type": "Bus",
                "bg_color": "#FF7800",
                "fg_color": "#FFFFFF",
                "product_icon": "/images/jpapi_hafas/bus.svg",
                "operator": "SVL"
            },
            "cancelled": false
        },
        {
            "stop_id": "",
            "headsign": "Bad Schwartau ZOB",
            "platform": "",
            "patform_type": "",
            "time": 1736586780,
            "realtime": 1736586780,
            "line": {
                "name": "9",
                "type": "Bus",
                "bg_color": "#FF7800",
                "fg_color": "#FFFFFF",
                "product_icon": "/images/jpapi_hafas/bus.svg",
                "operator": "SVL"
            },
            "cancelled": false
        },
        {
            "stop_id": "",
            "headsign": "Bad Schwartau ZOB",
            "platform": "",
            "patform_type": "",
            "time": 1736586900,
            "realtime": 1736586900,
            "line": {
                "name": "7",
                "type": "Bus",
                "bg_color": "#FF7800",
                "fg_color": "#FFFFFF",
                "product_icon": "/images/jpapi_hafas/bus.svg",
                "operator": "SVL"
            },
            "cancelled": false
        },
        {
            "stop_id": "",
            "headsign": "Bahnhof Moisling",
            "platform": "",
            "patform_type": "",
            "time": 1736586960,
            "realtime": 1736586960,
            "line": {
                "name": "7",
                "type": "Bus",
                "bg_color": "#FF7800",
                "fg_color": "#FFFFFF",
                "product_icon": "/images/jpapi_hafas/bus.svg",
                "operator": "SVL"
            },
            "cancelled": false
        },
        {
            "stop_id": "",
            "headsign": "Grillenweg",
            "platform": "",
            "patform_type": "",
            "time": 1736587140,
            "realtime": 1736587140,
            "line": {
                "name": "9",
                "type": "Bus",
                "bg_color": "#FF7800",
                "fg_color": "#FFFFFF",
                "product_icon": "/images/jpapi_hafas/bus.svg",
                "operator": "SVL"
            },
            "cancelled": false
        },
        {
            "stop_id": "",
            "headsign": "Bad Schwartau ZOB",
            "platform": "",
            "patform_type": "",
            "time": 1736588580,
            "realtime": 1736588580,
            "line": {
                "name": "9",
                "type": "Bus",
                "bg_color": "#FF7800",
                "fg_color": "#FFFFFF",
                "product_icon": "/images/jpapi_hafas/bus.svg",
                "operator": "SVL"
            },
            "cancelled": false
        },
        {
            "stop_id": "",
            "headsign": "Bad Schwartau ZOB",
            "platform": "",
            "patform_type": "",
            "time": 1736588700,
            "realtime": 1736588700,
            "line": {
                "name": "7",
                "type": "Bus",
                "bg_color": "#FF7800",
                "fg_color": "#FFFFFF",
                "product_icon": "/images/jpapi_hafas/bus.svg",
                "operator": "SVL"
            },
            "cancelled": false
        },
        {
            "stop_id": "",
            "headsign": "Bahnhof Moisling",
            "platform": "",
            "patform_type": "",
            "time": 1736588760,
            "realtime": 1736588760,
            "line": {
                "name": "7",
                "type": "Bus",
                "bg_color": "#FF7800",
                "fg_color": "#FFFFFF",
                "product_icon": "/images/jpapi_hafas/bus.svg",
                "operator": "SVL"
            },
            "cancelled": false
        },
        {
            "stop_id": "",
            "headsign": "Bornkamp",
            "platform": "",
            "patform_type": "",
            "time": 1736588940,
            "realtime": 1736588940,
            "line": {
                "name": "9",
                "type": "Bus",
                "bg_color": "#FF7800",
                "fg_color": "#FFFFFF",
                "product_icon": "/images/jpapi_hafas/bus.svg",
                "operator": "SVL"
            },
            "cancelled": false
        }
    ]
}