{
    "data": [
        {
            "stop_id": "",
            "headsign": "Grillenweg",
            "platform": "",
            "patform_type": "",
            "time": 1736546820,
            "realtime": 1736546820,
            "line": {
                "name": "9",
                "type": "Bus",
                "bg_color": "#FF7800",
                "fg_color": "#FFFFFF",
                "product_icon": "/images/jpapi_hafas/bus.svg",
                "operator": "SVL"
            },
            "cancelled": false
        },
        {
            "stop_id": "",
            "headsign": "Bad Schwartau ZOB",
            "platform": "",
            "patform_type": "",
            "time": 1736547780,
            "realtime": 1736547780,
            "line": {
                "name": "7",
                "type": "Bus",
                "bg_color": "#FF7800",
                "fg_color": "#FFFFFF",
                "product_icon": "/images/jpapi_hafas/bus.svg",
                "operator": "SVL"
            },
            "cancelled": false
        },
        {
            "stop_id": "",
            "headsign": "Stephensonstra\u00dfe",
            "platform": "",
            "patform_type": "",
            "time": 1736548620,
            "realtime": 1736548620,
            "line": {
                "name": "7",
                "type": "Bus",
                "bg_color": "#FF7800",
                "fg_color": "#FFFFFF",
                "product_icon": "/images/jpapi_hafas/bus.svg",
                "operator": "SVL"
            },
            "cancelled": false
        },
        {
            "stop_id": "",
            "headsign": "Bad Schwartau ZOB",
            "platform": "",
            "patform_type": "",
            "time": 1736549760,
            "realtime": 1736549760,
            "line": {
                "name": "9",
                "type": "Bus",
                "bg_color": "#FF7800",
                "fg_color": "#FFFFFF",
                "product_icon": "/images/jpapi_hafas/bus.svg",
                "operator": "SVL"
            },
            "cancelled": false
        },
        {
            "stop_id": "",
            "headsign": "ZOB/Hauptbahnhof",
            "platform": "",
            "patform_type": "",
            "time": 1736550420,
            "realtime": 1736550420,
            "line": {
                "name": "7",
                "type": "Bus",
                "bg_color": "#FF7800",
                "fg_color": "#FFFFFF",
                "product_icon": "/images/jpapi_hafas/bus.svg",
                "operator": "SVL"
            },
            "cancelled": false
        },
        {
            "stop_id": "",
            "headsign": "Bad Schwartau ZOB",
            "platform": "",
            "patform_type": "",
            "time": 1736551380,
            "realtime": 1736551380,
            "line": {
                "name": "7",
                "type": "Bus",
                "bg_color": "#FF7800",
                "fg_color": "#FFFFFF",
                "product_icon": "/images/jpapi_hafas/bus.svg",
                "operator": "SVL"
            },
            "cancelled": false
        },
        {
            "stop_id": "",
            "headsign": "Bad Schwartau ZOB",
            "platform": "",
            "patform_type": "",
            "time": 1736553360,
            "realtime": 1736553360,
            "line": {
                "name": "7",
                "type": "Bus",
                "bg_color": "#FF7800",
                "fg_color": "#FFFFFF",
                "product_icon": "/images/jpapi_hafas/bus.svg",
                "operator": "SVL"
            },
            "cancelled": false
        },
        {
            "stop_id": "",
            "headsign": "Bahnhof Moisling",
            "platform": "",
            "patform_type": "",
            "time": 1736568060,
            "realtime": 1736568060,
            "line": {
                "name": "7",
                "type": "Bus",
                "bg_color": "#FF7800",
                "fg_color": "#FFFFFF",
                "product_icon": "/images/jpapi_hafas/bus.svg",
                "operator": "SVL"
            },
            "cancelled": false
        },
        {
            "stop_id": "",
            "headsign": "Grillenweg",
            "platform": "",
            "patform_type": "",
            "time": 1736568840,
            "realtime": 1736568840,
            "line": {
                "name": "9",
                "type": "Bus",
                "bg_color": "#FF7800",
                "fg_color": "#FFFFFF",
                "product_icon": "/images/jpapi_hafas/bus.svg",
                "operator": "SVL"
            },
            "cancelled": false
        },
        {
            "stop_id": "",
            "headsign": "Bahnhof Moisling",
            "platform": "",
            "patform_type": "",
            "time": 1736569560,
            "realtime": 1736569560,
            "line": {
                "name": "7",
                "type": "Bus",
                "bg_color": "#FF7800",
                "fg_color": "#FFFFFF",
                "product_icon": "/images/jpapi_hafas/bus.svg",
                "operator": "SVL"
            },
            "cancelled": false
        },
        {
            "stop_id": "",
            "headsign": "Bad Schwartau ZOB",
            "platform": "",
            "patform_type": "",
            "time": 1736570760,
            "realtime": 1736570760,
            "line": {
                "name": "7",
                "type": "Bus",
                "bg_color": "#FF7800",
                "fg_color": "#FFFFFF",
                "product_icon": "/images/jpapi_hafas/bus.svg",
                "operator": "SVL"
            },
            "cancelled": false
        },
        {
            "stop_id": "",
            "headsign": "Bahnhof Moisling",
            "platform": "",
            "patform_type": "",
            "time": 1736571660,
            "realtime": 1736571660,
            "line": {
                "name": "7",
                "type": "Bus",
                "bg_color": "#FF7800",
                "fg_color": "#FFFFFF",
                "product_icon": "/images/jpapi_hafas/bus.svg",
                "operator": "SVL"
            },
            "cancelled": false
        },
        {
            "stop_id": "",
            "headsign": "Bad Schwartau ZOB",
            "platform": "",
            "patform_type": "",
            "time": 1736571780,
            "realtime": 1736571780,
            "line": {
                "name": "9",
                "type": "Bus",
                "bg_color": "#FF7800",
                "fg_color": "#FFFFFF",
                "product_icon": "/images/jpapi_hafas/bus.svg",
                "operator": "SVL"
            },
            "cancelled": false
        },
        {
            "stop_id": "",
            "headsign": "Bad Schwartau ZOB",
            "platform": "",
            "patform_type": "",
            "time": 1736572260,
            "realtime": 1736572260,
            "line": {
                "name": "7",
                "type": "Bus",
                "bg_color": "#FF7800",
                "fg_color": "#FFFFFF",
                "product_icon": "/images/jpapi_hafas/bus.svg",
                "operator": "SVL"
            },
            "cancelled": false
        },
        {
            "stop_id": "",
            "headsign": "Grillenweg",
            "platform": "",
            "patform_type": "",
            "time": 1736572440,
            "realtime": 1736572440,
            "line": {
                "name": "9",
                "type": "Bus",
                "bg_color": "#FF7800",
                "fg_color": "#FFFFFF",
                "product_icon": "/images/jpapi_hafas/bus.svg",
                "operator": "SVL"
            },
            "cancelled": false
        },
        {
            "stop_id": "",
            "headsign": "Bahnhof Moisling",
            "platform": "",
            "patform_type": "",
            "time": 1736573160,
            "realtime": 1736573160,
            "line": {
                "name": "7",
                "type": "Bus",
                "bg_color": "#FF7800",
                "fg_color": "#FFFFFF",
                "product_icon": "/images/jpapi_hafas/bus.svg",
                "operator": "SVL"
            },
            "cancelled": false
        },
        {
            "stop_id": "",
            "headsign": "Bad Schwartau ZOB",
            "platform": "",
            "patform_type": "",
            "time": 1736574360,
            "realtime": 1736574360,
            "line": {
                "name": "7",
                "type": "Bus",
                "bg_color": "#FF7800",
                "fg_color": "#FFFFFF",
                "product_icon": "/images/jpapi_hafas/bus.svg",
                "operator": "SVL"
            },
            "cancelled": false
        },
        {
            "stop_id": "",
            "headsign": "Bad Schwartau ZOB",
            "platform": "",
            "patform_type": "",
            "time": 1736575380,
            "realtime": 1736575380,
            "line": {
                "name": "9",
                "type": "Bus",
                "bg_color": "#FF7800",
                "fg_color": "#FFFFFF",
                "product_icon": "/images/jpapi_hafas/bus.svg",
                "operator": "SVL"
            },
            "cancelled": false
        },
        {
            "stop_id": "",
            "headsign": "Bahnhof Moisling",
            "platform": "",
            "patform_type": "",
            "time": 1736575740,
            "realtime": 1736575740,
            "line": {
                "name": "7",
                "type": "Bus",
                "bg_color": "#FF7800",
                "fg_color": "#FFFFFF",
                "product_icon": "/images/jpapi_hafas/bus.svg",
                "operator": "SVL"
            },
            "cancelled": false
        },
        {
            "stop_id": "",
            "headsign": "Bad Schwartau ZOB",
            "platform": "",
            "patform_type": "",
            "time": 1736575860,
            "realtime": 1736575860,
            "line": {
                "name": "7",
                "type": "Bus",
                "bg_color": "#FF7800",
                "fg_color": "#FFFFFF",
                "product_icon": "/images/jpapi_hafas/bus.svg",
                "operator": "SVL"
            },
            "cancelled": false
        },
        {
            "stop_id": "",
            "headsign": "Grillenweg",
            "platform": "",
            "patform_type": "",
            "time": 1736575920,
            "realtime": 1736575920,
            "line": {
                "name": "9",
                "type": "Bus",
                "bg_color": "#FF7800",
                "fg_color": "#FFFFFF",
                "product_icon": "/images/jpapi_hafas/bus.svg",
                "operator": "SVL"
            },
            "cancelled": false
        },
        {
            "stop_id": "",
            "headsign": "Bahnhof Moisling",
            "platform": "",
            "patform_type": "",
            "time": 1736577540,
            "realtime": 1736577540,
            "line": {
                "name": "7",
                "type": "Bus",
                "bg_color": "#FF7800",
                "fg_color": "#FFFFFF",
                "product_icon": "/images/jpapi_hafas/bus.svg",
                "operator": "SVL"
            },
            "cancelled": false
        },
        {
            "stop_id": "",
            "headsign": "Bad Schwartau ZOB",
            "platform": "",
            "patform_type": "",
            "time": 1736578380,
            "realtime": 1736578380,
            "line": {
                "name": "7",
                "type": "Bus",
                "bg_color": "#FF7800",
                "fg_color": "#FFFFFF",
                "product_icon": "/images/jpapi_hafas/bus.svg",
                "operator": "SVL"
            },
            "cancelled": false
        },
        {
            "stop_id": "",
            "headsign": "Bahnhof Moisling",
            "platform": "",
            "patform_type": "",
            "time": 1736579340,
            "realtime": 1736579340,
            "line": {
                "name": "7",
                "type": "Bus",
                "bg_color": "#FF7800",
                "fg_color": "#FFFFFF",
                "product_icon": "/images/jpapi_hafas/bus.svg",
                "operator": "SVL"
            },
            "cancelled": false
        },
        {
            "stop_id": "",
            "headsign": "Grillenweg",
            "platform": "",
            "patform_type": "",
            "time": 1736579520,
            "realtime": 1736579520,
            "line": {
                "name": "9",
                "type": "Bus",
                "bg_color": "#FF7800",
                "fg_color": "#FFFFFF",
                "product_icon": "/images/jpapi_hafas/bus.svg",
                "operator": "SVL"
            },
            "cancelled": false
        },
        {
            "stop_id": "",
            "headsign": "Bad Schwartau ZOB",
            "platform": "",
            "patform_type": "",
            "time": 1736580060,
            "realtime": 1736580060,
            "line": {
                "name": "9",
                "type": "Bus",
                "bg_color": "#FF7800",
                "fg_color": "#FFFFFF",
                "product_icon": "/images/jpapi_hafas/bus.svg",
                "operator": "SVL"
            },
            "cancelled": false
        },
        {
            "stop_id": "",
            "headsign": "Bad Schwartau ZOB",
            "platform": "",
            "patform_type": "",
            "time": 1736580180,
            "realtime": 1736580180,
            "line": {
                "name": "7",
                "type": "Bus",
                "bg_color": "#FF7800",
                "fg_color": "#FFFFFF",
                "product_icon": "/images/jpapi_hafas/bus.svg",
                "operator": "SVL"
            },
            "cancelled": false
        },
        {
            "stop_id": "",
            "headsign": "Bahnhof Moisling",
            "platform": "",
            "patform_type": "",
            "time": 1736581140,
            "realtime": 1736581140,
            "line": {
                "name": "7",
                "type": "Bus",
                "bg_color": "#FF7800",
                "fg_color": "#FFFFFF",
                "product_icon": "/images/jpapi_hafas/bus.svg",
                "operator": "SVL"
            },
            "cancelled": false
        },
        {
            "stop_id": "",
            "headsign": "Bornkamp",
            "platform": "",
            "patform_type": "",
            "time": 1736581320,
            "realtime": 1736581320,
            "line": {
                "name": "9",
                "type": "Bus",
                "bg_color": "#FF7800",
                "fg_color": "#FFFFFF",
                "product_icon": "/images/jpapi_hafas/bus.svg",
                "operator": "SVL"
            },
            "cancelled": false
        },
        {
            "stop_id": "",
            "headsign": "Bad Schwartau ZOB",
            "platform": "",
            "patform_type": "",
            "time": 1736581980,
            "realtime": 1736581980,
            "line": {
                "name": "7",
                "type": "Bus",
                "bg_color": "#FF7800",
                "fg_color": "#FFFFFF",
                "product_icon": "/images/jpapi_hafas/bus.svg",
                "operator": "SVL"
            },
            "cancelled": false
        },
        {
            "stop_id": "",
            "headsign": "Bahnhof Moisling",
            "platform": "",
            "patform_type": "",
            "time": 1736582940,
            "realtime": 1736582940,
            "line": {
                "name": "7",
                "type": "Bus",
                "bg_color": "#FF7800",
                "fg_color": "#FFFFFF",
                "product_icon": "/images/jpapi_hafas/bus.svg",
                "operator": "SVL"
            },
            "cancelled": false
        },
        {
            "stop_id": "",
            "headsign": "Grillenweg",
            "platform": "",
            "patform_type": "",
            "time": 1736583120,
            "realtime": 1736583120,
            "line": {
                "name": "9",
                "type": "Bus",
                "bg_color": "#FF7800",
                "fg_color": "#FFFFFF",
                "product_icon": "/images/jpapi_hafas/bus.svg",
                "operator": "SVL"
            },
            "cancelled": false
        },
        {
            "stop_id": "",
            "headsign": "Bad Schwartau ZOB",
            "platform": "",
            "patform_type": "",
            "time": 1736583660,
            "realtime": 1736583660,
            "line": {
                "name": "9",
                "type": "Bus",
                "bg_color": "#FF7800",
                "fg_color": "#FFFFFF",
                "product_icon": "/images/jpapi_hafas/bus.svg",
                "operator": "SVL"
            },
            "cancelled": false
        },
        {
            "stop_id": "",
            "headsign": "Bad Schwartau ZOB",
            "platform": "",
            "patform_type": "",
            "time": 1736583780,
            "realtime": 1736583780,
            "line": {
                "name": "7",
                "type": "Bus",
                "bg_color": "#FF7800",
                "fg_color": "#FFFFFF",
                "product_icon": "/images/jpapi_hafas/bus.svg",
                "operator": "SVL"
            },
            "cancelled": false
        },
        {
            "stop_id": "",
            "headsign": "Bahnhof Moisling",
            "platform": "",
            "patform_type": "",
            "time": 1736584740,
            "realtime": 1736584740,
            "line": {
                "name": "7",
                "type": "Bus",
                "bg_color": "#FF7800",
                "fg_color": "#FFFFFF",
                "product_icon": "/images/jpapi_hafas/bus.svg",
                "operator": "SVL"
            },
            "cancelled": false
        },
        {
            "stop_id": "",
            "headsign": "Bornkamp",
            "platform": "",
            "patform_type": "",
            "time": 1736584920,
            "realtime": 1736584920,
            "line": {
                "name": "9",
                "type": "Bus",
                "bg_color": "#FF7800",
                "fg_color": "#FFFFFF",
                "product_icon": "/images/jpapi_hafas/bus.svg",
                "operator": "SVL"
            },
            "cancelled": false
        },
        {
            "stop_id": "",
            "headsign": "Bad Schwartau ZOB",
            "platform": "",
            "patform_type": "",
            "time": 1736585460,
            "realtime": 1736585460,
            "line": {
                "name": "9",
                "type": "Bus",
                "bg_color": "#FF7800",
                "fg_color": "#FFFFFF",
                "product_icon": "/images/jpapi_hafas/bus.svg",
                "operator": "SVL"
            },
            "cancelled": false
        },
        {
            "stop_id": "",
            "headsign": "Bad Schwartau ZOB",
            "platform": "",
            "patform_type": "",
            "time": 1736585580,
            "realtime": 1736585580,
            "line": {
                "name": "7",
                "type": "Bus",
                "bg_color": "#FF7800",
                "fg_color": "#FFFFFF",
                "product_icon": "/images/jpapi_hafas/bus.svg",
                "operator": "SVL"
            },
            "cancelled": false
        },
        {
            "stop_id": "",
            "headsign": "Bahnhof Moisling",
            "platform": "",
            "patform_type": "",
            "time": 1736586540,
            "realtime": 1736586540,
            "line": {
                "name": "7",
                "type": "Bus",
                "bg_color": "#FF7800",
                "fg_color": "#FFFFFF",
                "product_icon": "/images/jpapi_hafas/bus.svg",
                "operator": "SVL"
            },
            "cancelled": false
        },
        {
            "stop_id": "",
            "headsign": "Grillenweg",
            "platform": "",
            "patform_type": "",
            "time": 1736586720,
            "realtime": 1736586720,
            "line": {
                "name": "9",
                "type": "Bus",
                "bg_color": "#FF7800",
                "fg_color": "#FFFFFF",
                "product_icon": "/images/jpapi_hafas/bus.svg",
                "operator": "SVL"
            },
            "cancelled": false
        },
        {
            "stop_id": "",
            "headsign": "Bad Schwartau ZOB",
            "platform": "",
            "patform_type": "",
            "time": 1736587260,
            "realtime": 1736587260,
            "line": {
                "name": "9",
                "type": "Bus",
                "bg_color": "#FF7800",
                "fg_color": "#FFFFFF",
                "product_icon": "/images/jpapi_hafas/bus.svg",
                "operator": "SVL"
            },
            "cancelled": false
        },
        {
            "stop_id": "",
            "headsign": "Bad Schwartau ZOB",
            "platform": "",
            "patform_type": "",
            "time": 1736587380,
            "realtime": 1736587380,
            "line": {
                "name": "7",
                "type": "Bus",
                "bg_color": "#FF7800",
                "fg_color": "#FFFFFF",
                "product_icon": "/images/jpapi_hafas/bus.svg",
                "operator": "SVL"
            },
            "cancelled": false
        },
        {
            "stop_id": "",
            "headsign": "Bahnhof Moisling",
            "platform": "",
            "patform_type": "",
            "time": 1736588340,
            "realtime": 1736588340,
            "line": {
                "name": "7",
                "type": "Bus",
                "bg_color": "#FF7800",
                "fg_color": "#FFFFFF",
                "product_icon": "/images/jpapi_hafas/bus.svg",
                "operator": "SVL"
            },
            "cancelled": false
        },
        {
            "stop_id": "",
            "headsign": "Bornkamp",
            "platform": "",
            "patform_type": "",
            "time": 1736588520,
            "realtime": 1736588520,
            "line": {
                "name": "9",
                "type": "Bus",
                "bg_color": "#FF7800",
                "fg_color": "#FFFFFF",
                "product_icon": "/images/jpapi_hafas/bus.svg",
                "operator": "SVL"
            },
            "cancelled": false
        },
        {
            "stop_id": "",
            "headsign": "Bad Schwartau ZOB",
            "platform": "",
            "patform_type": "",
            "time": 1736589060,
            "realtime": 1736589060,
            "line": {
                "name": "9",
                "type": "Bus",
                "bg_color": "#FF7800",
                "fg_color": "#FFFFFF",
                "product_icon": "/images/jpapi_hafas/bus.svg",
                "operator": "SVL"
            },
            "cancelled": false
        },
        {
            "stop_id": "",
            "headsign": "Bad Schwartau ZOB",
            "platform": "",
            "patform_type": "",
            "time": 1736589180,
            "realtime": 1736589180,
            "line": {
                "name": "7",
                "type": "Bus",
                "bg_color": "#FF7800",
                "fg_color": "#FFFFFF",
                "product_icon": "/images/jpapi_hafas/bus.svg",
                "operator": "SVL"
            },
            "cancelled": false
        }
    ]
}