{
    "data": [
        {
            "stop_id": "",
            "headsign": "Grillenweg",
            "platform": "",
            "patform_type": "",
            "time": 1736484120,
            "realtime": 1736484120,
            "line": {
                "name": "9",
                "type": "Bus",
                "bg_color": "#FF7800",
                "fg_color": "#FFFFFF",
                "product_icon": "/images/jpapi_hafas/bus.svg",
                "operator": "SVL"
            },
            "cancelled": false
        },
        {
            "stop_id": "",
            "headsign": "Bad Schwartau ZOB",
            "platform": "",
            "patform_type": "",
            "time": 1736485200,
            "realtime": 1736485200,
            "line": {
                "name": "9",
                "type": "Bus",
                "bg_color": "#FF7800",
                "fg_color": "#FFFFFF",
                "product_icon": "/images/jpapi_hafas/bus.svg",
                "operator": "SVL"
            },
            "cancelled": false
        },
        {
            "stop_id": "",
            "headsign": "Grillenweg",
            "platform": "",
            "patform_type": "",
            "time": 1736486940,
            "realtime": 1736486940,
            "line": {
                "name": "9",
                "type": "Bus",
                "bg_color": "#FF7800",
                "fg_color": "#FFFFFF",
                "product_icon": "/images/jpapi_hafas/bus.svg",
                "operator": "SVL"
            },
            "cancelled": false
        },
        {
            "stop_id": "",
            "headsign": "Grillenweg",
            "platform": "",
            "patform_type": "",
            "time": 1736488740,
            "realtime": 1736488740,
            "line": {
                "name": "9",
                "type": "Bus",
                "bg_color": "#FF7800",
                "fg_color": "#FFFFFF",
                "product_icon": "/images/jpapi_hafas/bus.svg",
                "operator": "SVL"
            },
            "cancelled": false
        },
        {
            "stop_id": "",
            "headsign": "Bad Schwartau ZOB",
            "platform": "",
            "patform_type": "",
            "time": 1736488800,
            "realtime": 1736488800,
            "line": {
                "name": "9",
                "type": "Bus",
                "bg_color": "#FF7800",
                "fg_color": "#FFFFFF",
                "product_icon": "/images/jpapi_hafas/bus.svg",
                "operator": "SVL"
            },
            "cancelled": false
        },
        {
            "stop_id": "",
            "headsign": "Grillenweg",
            "platform": "",
            "patform_type": "",
            "time": 1736490540,
            "realtime": 1736490540,
            "line": {
                "name": "9",
                "type": "Bus",
                "bg_color": "#FF7800",
                "fg_color": "#FFFFFF",
                "product_icon": "/images/jpapi_hafas/bus.svg",
                "operator": "SVL"
            },
            "cancelled": false
        },
        {
            "stop_id": "",
            "headsign": "Bad Schwartau ZOB",
            "platform": "",
            "patform_type": "",
            "time": 1736490600,
            "realtime": 1736490600,
            "line": {
                "name": "9",
                "type": "Bus",
                "bg_color": "#FF7800",
                "fg_color": "#FFFFFF",
                "product_icon": "/images/jpapi_hafas/bus.svg",
                "operator": "SVL"
            },
            "cancelled": false
        },
        {
            "stop_id": "",
            "headsign": "Grillenweg",
            "platform": "",
            "patform_type": "",
            "time": 1736492340,
            "realtime": 1736492340,
            "line": {
                "name": "9",
                "type": "Bus",
                "bg_color": "#FF7800",
                "fg_color": "#FFFFFF",
                "product_icon": "/images/jpapi_hafas/bus.svg",
                "operator": "SVL"
            },
            "cancelled": false
        },
        {
            "stop_id": "",
            "headsign": "Bad Schwartau ZOB",
            "platform": "",
            "patform_type": "",
            "time": 1736492400,
            "realtime": 1736492400,
            "line": {
                "name": "9",
                "type": "Bus",
                "bg_color": "#FF7800",
                "fg_color": "#FFFFFF",
                "product_icon": "/images/jpapi_hafas/bus.svg",
                "operator": "SVL"
            },
            "cancelled": false
        },
        {
            "stop_id": "",
            "headsign": "Grillenweg",
            "platform": "",
            "patform_type": "",
            "time": 1736494140,
            "realtime": 1736494140,
            "line": {
                "name": "9",
                "type": "Bus",
                "bg_color": "#FF7800",
                "fg_color": "#FFFFFF",
                "product_icon": "/images/jpapi_hafas/bus.svg",
                "operator": "SVL"
            },
            "cancelled": false
        },
        {
            "stop_id": "",
            "headsign": "Bad Schwartau ZOB",
            "platform": "",
            "patform_type": "",
            "time": 1736494200,
            "realtime": 1736494200,
            "line": {
                "name": "9",
                "type": "Bus",
                "bg_color": "#FF7800",
                "fg_color": "#FFFFFF",
                "product_icon": "/images/jpapi_hafas/bus.svg",
                "operator": "SVL"
            },
            "cancelled": false
        },
        {
            "stop_id": "",
            "headsign": "Grillenweg",
            "platform": "",
            "patform_type": "",
            "time": 1736495940,
            "realtime": 1736495940,
            "line": {
                "name": "9",
                "type": "Bus",
                "bg_color": "#FF7800",
                "fg_color": "#FFFFFF",
                "product_icon": "/images/jpapi_hafas/bus.svg",
                "operator": "SVL"
            },
            "cancelled": false
        },
        {
            "stop_id": "",
            "headsign": "Bad Schwartau ZOB",
            "platform": "",
            "patform_type": "",
            "time": 1736496000,
            "realtime": 1736496000,
            "line": {
                "name": "9",
                "type": "Bus",
                "bg_color": "#FF7800",
                "fg_color": "#FFFFFF",
                "product_icon": "/images/jpapi_hafas/bus.svg",
                "operator": "SVL"
            },
            "cancelled": false
        },
        {
            "stop_id": "",
            "headsign": "Grillenweg",
            "platform": "",
            "patform_type": "",
            "time": 1736497740,
            "realtime": 1736497740,
            "line": {
                "name": "9",
                "type": "Bus",
                "bg_color": "#FF7800",
                "fg_color": "#FFFFFF",
                "product_icon": "/images/jpapi_hafas/bus.svg",
                "operator": "SVL"
            },
            "cancelled": false
        },
        {
            "stop_id": "",
            "headsign": "Bad Schwartau ZOB",
            "platform": "",
            "patform_type": "",
            "time": 1736497800,
            "realtime": 1736497800,
            "line": {
                "name": "9",
                "type": "Bus",
                "bg_color": "#FF7800",
                "fg_color": "#FFFFFF",
                "product_icon": "/images/jpapi_hafas/bus.svg",
                "operator": "SVL"
            },
            "cancelled": false
        },
        {
            "stop_id": "",
            "headsign": "Grillenweg",
            "platform": "",
            "patform_type": "",
            "time": 1736499540,
            "realtime": 1736499540,
            "line": {
                "name": "9",
                "type": "Bus",
                "bg_color": "#FF7800",
                "fg_color": "#FFFFFF",
                "product_icon": "/images/jpapi_hafas/bus.svg",
                "operator": "SVL"
            },
            "cancelled": false
        },
        {
            "stop_id": "",
            "headsign": "Bad Schwartau ZOB",
            "platform": "",
            "patform_type": "",
            "time": 1736499600,
            "realtime": 1736499600,
            "line": {
                "name": "9",
                "type": "Bus",
                "bg_color": "#FF7800",
                "fg_color": "#FFFFFF",
                "product_icon": "/images/jpapi_hafas/bus.svg",
                "operator": "SVL"
            },
            "cancelled": false
        },
        {
            "stop_id": "",
            "headsign": "Grillenweg",
            "platform": "",
            "patform_type": "",
            "time": 1736501340,
            "realtime": 1736501340,
            "line": {
                "name": "9",
                "type": "Bus",
                "bg_color": "#FF7800",
                "fg_color": "#FFFFFF",
                "product_icon": "/images/jpapi_hafas/bus.svg",
                "operator": "SVL"
            },
            "cancelled": false
        },
        {
            "stop_id": "",
            "headsign": "Bad Schwartau ZOB",
            "platform": "",
            "patform_type": "",
            "time": 1736501400,
            "realtime": 1736501400,
            "line": {
                "name": "9",
                "type": "Bus",
                "bg_color": "#FF7800",
                "fg_color": "#FFFFFF",
                "product_icon": "/images/jpapi_hafas/bus.svg",
                "operator": "SVL"
            },
            "cancelled": false
        },
        {
            "stop_id": "",
            "headsign": "Grillenweg",
            "platform": "",
            "patform_type": "",
            "time": 1736503140,
            "realtime": 1736503140,
            "line": {
                "name": "9",
                "type": "Bus",
                "bg_color": "#FF7800",
                "fg_color": "#FFFFFF",
                "product_icon": "/images/jpapi_hafas/bus.svg",
                "operator": "SVL"
            },
            "cancelled": false
        },
        {
            "stop_id": "",
            "headsign": "Bad Schwartau ZOB",
            "platform": "",
            "patform_type": "",
            "time": 1736503200,
            "realtime": 1736503200,
            "line": {
                "name": "9",
                "type": "Bus",
                "bg_color": "#FF7800",
                "fg_color": "#FFFFFF",
                "product_icon": "/images/jpapi_hafas/bus.svg",
                "operator": "SVL"
            },
            "cancelled": false
        },
        {
            "stop_id": "",
            "headsign": "Grillenweg",
            "platform": "",
            "patform_type": "",
            "time": 1736504940,
            "realtime": 1736504940,
            "line": {
                "name": "9",
                "type": "Bus",
                "bg_color": "#FF7800",
                "fg_color": "#FFFFFF",
                "product_icon": "/images/jpapi_hafas/bus.svg",
                "operator": "SVL"
            },
            "cancelled": false
        },
        {
            "stop_id": "",
            "headsign": "Bad Schwartau ZOB",
            "platform": "",
            "patform_type": "",
            "time": 1736505000,
            "realtime": 1736505000,
            "line": {
                "name": "9",
                "type": "Bus",
                "bg_color": "#FF7800",
                "fg_color": "#FFFFFF",
                "product_icon": "/images/jpapi_hafas/bus.svg",
                "operator": "SVL"
            },
            "cancelled": false
        }
    ]
}